hedera_defi/__init__.py
hedera_defi/client.py
hedera_defi/models.py
hedera_defi/utils.py
hedera_defi-0.3.0.dist-info/LICENSE
hedera_defi-0.3.0.dist-info/METADATA
hedera_defi-0.3.0.dist-info/WHEEL
hedera_defi-0.3.0.dist-info/top_level.txt
hedera_defi-0.3.0.dist-info/RECORD
