Metadata-Version: 2.1
Name: hedera-defi
Version: 0.3.0
Summary: Comprehensive Python SDK for Hedera DeFi analytics with SaucerSwap DEX & Bonzo Finance integration
Author-email: Sam Savage <admin@quantdefi.ai>
License: MIT
Project-URL: Homepage, https://github.com/samthedataman/hedera-defi-sdk
Project-URL: Repository, https://github.com/samthedataman/hedera-defi-sdk
Project-URL: Issues, https://github.com/samthedataman/hedera-defi-sdk/issues
Keywords: hedera,defi,blockchain,analytics,mirror-node,cryptocurrency
Classifier: Development Status :: 4 - Beta
Classifier: Intended Audience :: Developers
Classifier: Topic :: Software Development :: Libraries :: Python Modules
Classifier: License :: OSI Approved :: MIT License
Classifier: Programming Language :: Python :: 3
Classifier: Programming Language :: Python :: 3.8
Classifier: Programming Language :: Python :: 3.9
Classifier: Programming Language :: Python :: 3.10
Classifier: Programming Language :: Python :: 3.11
Classifier: Operating System :: OS Independent
Requires-Python: >=3.8
License-File: LICENSE
Requires-Dist: requests >=2.28.0
Requires-Dist: pandas >=1.5.0
Requires-Dist: numpy >=1.21.0
Requires-Dist: python-dateutil >=2.8.0
Requires-Dist: typing-extensions >=4.0.0
Provides-Extra: dev
Requires-Dist: pytest >=7.0.0 ; extra == 'dev'
Requires-Dist: black >=22.0.0 ; extra == 'dev'
Requires-Dist: flake8 >=4.0.0 ; extra == 'dev'
Requires-Dist: mypy >=0.950 ; extra == 'dev'
